<?xml version="1.0" encoding="utf-8"?>
<databaseChangeLog
        xmlns:xsi="http://www.w3.org/2001/XMLSchema-instance"
        xmlns="http://www.liquibase.org/xml/ns/dbchangelog"
        xsi:schemaLocation="http://www.liquibase.org/xml/ns/dbchangelog http://www.liquibase.org/xml/ns/dbchangelog/dbchangelog-3.9.xsd">

    <property name="autoIncrement" value="true"/>

    <changeSet id="00000000000001" author="gudeck">
        <createTable tableName="CLASSE">
            <column name="ID" type="BIGINT" autoIncrement="${autoIncrement}">
                <constraints primaryKey="true" nullable="false"/>
            </column>
            <column name="NOME" type="VARCHAR(80)">
                <constraints nullable="false"/>
            </column>
            <column name="VALOR" type="DOUBLE">
                <constraints nullable="false"/>
            </column>
            <column name="PRAZO_DEVOLUCAO" type="INTEGER">
                <constraints nullable="false"/>
            </column>
        </createTable>
    </changeSet>

</databaseChangeLog>
